{
    "type": "object",
    "properties": {
        "id": {
            "type": [
                "null",
                "string"
            ]
        },
        "name": {
            "type": [
                "null",
                "string"
            ]
        },
        "picture_url": {
            "type": [
                "null",
                "string"
            ]
        },
        "owners": {
            "type": [
                "null",
                "array"
            ],
            "items": {
                "type": "object",
                "properties": {
                    "id": {
                        "type": [
                            "null",
                            "string"
                        ]
                    },
                    "name": {
                        "type": [
                            "null",
                            "string"
                        ]
                    }
                },
                "additionalProperties": true
            }
        },
        "users": {
            "type": [
                "null",
                "array"
            ],
            "items": {
                "type": "object",
                "properties": {
                    "id": {
                        "type": [
                            "null",
                            "string"
                        ]
                    },
                    "name": {
                        "type": [
                            "null",
                            "string"
                        ]
                    }
                },
                "additionalProperties": true
            }
        }
    },
    "additionalProperties": true
}
